easyeditor/__init__.py
easyeditor/dataset/__init__.py
easyeditor/dataset/attr_snippets.py
easyeditor/dataset/coco_caption.py
easyeditor/dataset/counterfact.py
easyeditor/dataset/knowns.py
easyeditor/dataset/tfidf_stats.py
easyeditor/dataset/vqa.py
easyeditor/dataset/wiki_recent.py
easyeditor/dataset/zsre.py
easyeditor/dataset/processor/base_dataset.py
easyeditor/dataset/processor/base_processor.py
easyeditor/dataset/processor/blip_processors.py
easyeditor/dataset/processor/randaugment.py
easyeditor/editors/__init__.py
easyeditor/editors/batch_editor.py
easyeditor/editors/editor.py
easyeditor/editors/multimodal_editor.py
easyeditor/editors/singleton_editor.py
easyeditor/evaluate/__init__.py
easyeditor/evaluate/evaluate.py
easyeditor/evaluate/evaluate_utils.py
easyeditor/evaluate/portability_evaluate.py
easyeditor/models/README.md
easyeditor/models/__init__.py
easyeditor/models/ft/__init__.py
easyeditor/models/ft/ft_hparams.py
easyeditor/models/ft/ft_main.py
easyeditor/models/ft_api/__init__.py
easyeditor/models/ft_api/ft_api_hparams.py
easyeditor/models/ft_api/ft_api_main.py
easyeditor/models/ike/__init__.py
easyeditor/models/ike/ike_hparams.py
easyeditor/models/ike/ike_main.py
easyeditor/models/ike/util.py
easyeditor/models/kn/__init__.py
easyeditor/models/kn/kn_hparams.py
easyeditor/models/kn/kn_main.py
easyeditor/models/kn/knowledge_neurons/LICENSE
easyeditor/models/kn/knowledge_neurons/README.md
easyeditor/models/kn/knowledge_neurons/pararel_evaluate.py
easyeditor/models/kn/knowledge_neurons/plot_pararel_results.py
easyeditor/models/kn/knowledge_neurons/requirements.txt
easyeditor/models/kn/knowledge_neurons/setup.py
easyeditor/models/kn/knowledge_neurons/knowledge_neurons/__init__.py
easyeditor/models/kn/knowledge_neurons/knowledge_neurons/data.py
easyeditor/models/kn/knowledge_neurons/knowledge_neurons/knowledge_neurons.py
easyeditor/models/kn/knowledge_neurons/knowledge_neurons/patch.py
easyeditor/models/kn/knowledge_neurons/tests/tests.py
easyeditor-0.0.1.dev0.dist-info/LICENSE
easyeditor-0.0.1.dev0.dist-info/METADATA
easyeditor-0.0.1.dev0.dist-info/WHEEL
easyeditor-0.0.1.dev0.dist-info/top_level.txt
easyeditor-0.0.1.dev0.dist-info/RECORD
