Metadata-Version: 2.1
Name: easyeditor
Version: 0.0.1.dev0
Summary: easyeditor - Editing Large Language Models
Author: Shadow Walker
Keywords: easyeditor
Classifier: Programming Language :: Python :: 3
Classifier: Programming Language :: Python :: 3.8
Classifier: Programming Language :: Python :: 3.9
Classifier: Programming Language :: Python :: 3.10
Classifier: Programming Language :: Python :: 3.11
License-File: LICENSE
Requires-Dist: datasets ==1.18.3
Requires-Dist: einops ==0.4.0
Requires-Dist: gpustat ==1.1
Requires-Dist: hydra-core ==1.1.1
Requires-Dist: higher ==0.2.1
Requires-Dist: importlib-metadata ==6.3.0
Requires-Dist: matplotlib ==3.5.1
Requires-Dist: nltk ==3.6.5
Requires-Dist: numpy ==1.22.1
Requires-Dist: omegaconf ==2.1.1
Requires-Dist: pandas ==1.4.0
Requires-Dist: PyYAML ==6.0
Requires-Dist: scikit-learn ==1.0.2
Requires-Dist: scipy ==1.7.3
Requires-Dist: sentence-transformers ==2.2.2
Requires-Dist: tokenizers ==0.13.3
Requires-Dist: torch ==2.0.1
Requires-Dist: tqdm ==4.62.3
Requires-Dist: transformers ==4.30.1
Requires-Dist: openai ==0.27.9
Requires-Dist: peft ==0.5.0
Requires-Dist: timm ==0.9.7
Requires-Dist: iopath ==0.1.10
Requires-Dist: opencv-python ==4.8.0.76
